unimenu/__init__.py
unimenu/core.py
unimenu/utils.py
unimenu/apps/__init__.py
unimenu/apps/_abstract.py
unimenu/apps/blender.py
unimenu/apps/marmoset.py
unimenu/apps/max.py
unimenu/apps/maya.py
unimenu/apps/qt.py
unimenu/apps/unreal.py
unimenu-3.0.0.dist-info/METADATA
unimenu-3.0.0.dist-info/WHEEL
unimenu-3.0.0.dist-info/top_level.txt
unimenu-3.0.0.dist-info/RECORD
