Metadata-Version: 2.1
Name: unimenu
Version: 3.0.0
Summary: easy menus from a single config across apps
Author: hannes
Project-URL: Homepage, https://github.com/hannesdelbeke/unimenu
Project-URL: Documentation, https://github.com/hannesdelbeke/unimenu/wiki
Keywords: dcc,pipeline,menu,config
Classifier: Programming Language :: Python :: 3.7
Requires-Python: >=3.4
Requires-Dist: importlib-metadata ; python_version < "3.7"
Provides-Extra: yaml
Requires-Dist: pyyaml ; extra == 'yaml'
